deepseek_chat/__init__.py
deepseek_chat/client.py
deepseek_chat/config.py
deepseek_chat/exceptions.py
deepseek_chat/filestore.py
deepseek_chat/logging_config.py
deepseek_chat/schema.py
deepseek_chat/service.py
deepseek_chat/store.py
deepseek_chat/utils.py
deepseek_chat-0.1.1.dist-info/licenses/LICENSE
deepseek_chat-0.1.1.dist-info/METADATA
deepseek_chat-0.1.1.dist-info/WHEEL
deepseek_chat-0.1.1.dist-info/top_level.txt
deepseek_chat-0.1.1.dist-info/RECORD
