Metadata-Version: 2.4
Name: deepseek_chat
Version: 0.1.1
Summary: Thin DeepSeek Chat wrapper with Mongo-backed conversation tree.
Author-email: bonecard <guxiaowa77@gmail.com>
License: MIT
License-File: LICENSE
Requires-Dist: requests>=2.31
Requires-Dist: pymongo>=4.6
Requires-Dist: pydantic>=2.7
Requires-Dist: pydantic-settings>=2.0
Requires-Dist: tiktoken>=0.6
Provides-Extra: dev
Requires-Dist: pytest>=8; extra == "dev"
Requires-Dist: ruff; extra == "dev"
Dynamic: license-file
